{
  "type": "Compass Connections",
  "version": {
    "$numberInt": "1"
  },
  "connections": [
    {
      "id": "9d8ec5fb-1796-4bae-8463-88c1c2d4373c",
      "lastUsed": {
        "$date": {
          "$numberLong": "1727258849080"
        }
      },
      "favorite": {
        "name": ""
      },
      "savedConnectionType": "recent",
      "connectionOptions": {
        "connectionString": "mongodb://localhost:27017/",
        "oidc": {
          "serializedState": "eyJvaWRjUGx1Z2luU3RhdGVWZXJzaW9uIjowLCJzdGF0ZSI6W119"
        }
      }
    }
  ]
}